{"chunk_definitions":[{"row":96,"row_count":1,"visible":true,"expansion_state":0,"options":{"engine":"r","label":"unnamed-chunk-61","dev":"png"},"document_id":"89855C3C","chunk_id":"cctb91jypfyc8","chunk_label":"unnamed-chunk-1"},{"row":162,"row_count":1,"visible":true,"expansion_state":0,"options":{"engine":"r","label":"unnamed-chunk-62","dev":"png"},"document_id":"89855C3C","chunk_id":"cbk8x0hxvhvxv","chunk_label":"unnamed-chunk-2"},{"row":365,"row_count":1,"visible":true,"expansion_state":0,"options":{"engine":"r","label":"unnamed-chunk-110","dev":"png"},"document_id":"89855C3C","chunk_id":"c501wxs9o5ysf","chunk_label":""},{"row":579,"row_count":1,"visible":true,"expansion_state":0,"options":{"engine":"r","label":"unnamed-chunk-111","dev":"png"},"document_id":"89855C3C","chunk_id":"cmb0581qskiar","chunk_label":"unnamed-chunk-5"},{"row":786,"row_count":1,"visible":true,"expansion_state":0,"options":{"engine":"r","label":"unnamed-chunk-112","dev":"png"},"document_id":"89855C3C","chunk_id":"cikq9zt8ok2f8","chunk_label":"unnamed-chunk-6"},{"row":994,"row_count":1,"visible":true,"expansion_state":0,"options":{"engine":"r","label":"unnamed-chunk-113","dev":"png"},"document_id":"89855C3C","chunk_id":"cvc37awmcatwk","chunk_label":""}],"doc_write_time":1730397950,"chunk_rendered_width":620}